odoo/addons/mrp_set_quantity_to_reservation/README.rst
odoo/addons/mrp_set_quantity_to_reservation/__init__.py
odoo/addons/mrp_set_quantity_to_reservation/__manifest__.py
odoo/addons/mrp_set_quantity_to_reservation/i18n/es.po
odoo/addons/mrp_set_quantity_to_reservation/i18n/mrp_set_quantity_to_reservation.pot
odoo/addons/mrp_set_quantity_to_reservation/models/__init__.py
odoo/addons/mrp_set_quantity_to_reservation/models/mrp_production.py
odoo/addons/mrp_set_quantity_to_reservation/readme/CONTRIBUTORS.rst
odoo/addons/mrp_set_quantity_to_reservation/readme/DESCRIPTION.rst
odoo/addons/mrp_set_quantity_to_reservation/static/description/icon.png
odoo/addons/mrp_set_quantity_to_reservation/static/description/index.html
odoo/addons/mrp_set_quantity_to_reservation/tests/__init__.py
odoo/addons/mrp_set_quantity_to_reservation/tests/test_mrp_set_quantity_to_reservation.py
odoo/addons/mrp_set_quantity_to_reservation/views/mrp_production_views.xml
odoo_addon_mrp_set_quantity_to_reservation-15.0.0.1.0.2.dist-info/METADATA
odoo_addon_mrp_set_quantity_to_reservation-15.0.0.1.0.2.dist-info/WHEEL
odoo_addon_mrp_set_quantity_to_reservation-15.0.0.1.0.2.dist-info/top_level.txt
odoo_addon_mrp_set_quantity_to_reservation-15.0.0.1.0.2.dist-info/RECORD
